imitatebias/LICENSE
imitatebias/__init__.py
imitatebias/cancels.py
imitatebias/generators.py
imitatebias/imitate.py
imitatebias/mimic.py
imitatebias-1.1.4.dist-info/METADATA
imitatebias-1.1.4.dist-info/WHEEL
imitatebias-1.1.4.dist-info/licenses/LICENSE
imitatebias-1.1.4.dist-info/RECORD
