Metadata-Version: 2.3
Name: imitatebias
Version: 1.1.4
Summary: Package for imitatebias
Project-URL: Homepage, https://github.com/KatDost/imitatebias
Project-URL: Bug Tracker, https://github.com/KatDost/imitatebias/issues
Project-URL: Documentation, https://katdost.github.io/imitatebias/
Author-email: Katharina Dost <k_dost@ymail.com>
License: GNU General Public License v3.0
License-File: LICENSE
Classifier: License :: OSI Approved :: GNU General Public License v3 (GPLv3)
Classifier: Operating System :: OS Independent
Classifier: Programming Language :: Python :: 3
Requires-Python: >=3.7
Requires-Dist: matplotlib
Requires-Dist: scikit-learn
Requires-Dist: statsmodels
